README.md
setup.py
datagene/__init__.py
datagene/dist_utilities.py
datagene/distance.py
datagene/mod_utilities.py
datagene/transform.py
datagene/vis_utilities.py
datagene.egg-info/PKG-INFO
datagene.egg-info/SOURCES.txt
datagene.egg-info/dependency_links.txt
datagene.egg-info/not-zip-safe
datagene.egg-info/requires.txt
datagene.egg-info/top_level.txt