Metadata-Version: 1.0
Name: datagene
Version: 0.0.2
Summary: Data Comparison Toolbox with Transformation and Similarity Analysis
Home-page: https://github.com/firmai/datagene
Author: snowde
Author-email: d.snow@firmai.org
License: MIT
Platform: UNKNOWN
